README.md
pyproject.toml
setup.py
compression_cache/__init__.py
compression_cache/main.py
compression_cache/models.py
compression_cache.egg-info/PKG-INFO
compression_cache.egg-info/SOURCES.txt
compression_cache.egg-info/dependency_links.txt
compression_cache.egg-info/not-zip-safe
compression_cache.egg-info/requires.txt
compression_cache.egg-info/top_level.txt