Metadata-Version: 2.2
Name: compression-cache
Version: 0.0.24
Summary: Python function caching with compression
Home-page: https://github.com/AMarsel2551/compression-cache
Author-email: m.adbullinn@gmail.com
Project-URL: Source Code, https://github.com/AMarsel2551/compression-cache.git
Project-URL: Documentation, https://github.com/AMarsel2551/compression-cache/wiki
Requires-Dist: zstandard==0.23.0
Requires-Dist: redis==5.2.1
Requires-Dist: pydantic==2.11.7
Requires-Dist: ujson==5.10.0
Dynamic: author-email
Dynamic: description
Dynamic: description-content-type
Dynamic: home-page
Dynamic: project-url
Dynamic: requires-dist
Dynamic: summary
